{
  "hero": [
    {
      "h1": "Marketing Digital focado em seus resultados !",
      "h4": "Cresça de forma inteligente com estratégias que combinam anúncios pagos e decisões guiadas por dados. Aumente sua presença, escale suas vendas e veja resultados reais.",
      "btn": "Comece a Crescer",
      "btnLink": "cta",
      "bgImg": "/assets/bg-hero.png",
      "logosClients": [
        {
          "image": "/assets/clients/logo-client-01.png",
          "alt": "Logo Cliente"
        },
        {
          "image": "/assets/clients/logo-client-02.png",
          "alt": "Logo Cliente"
        },
        {
          "image": "/assets/clients/logo-client-03.png",
          "alt": "Logo Cliente"
        },
        {
          "image": "/assets/clients/logo-client-04.png",
          "alt": "Logo Cliente"
        },
        {
          "image": "/assets/clients/logo-client-05.png",
          "alt": "Logo Cliente"
        },
        {
          "image": "/assets/clients/logo-client-06.png",
          "alt": "Logo Cliente"
        },
        {
          "image": "/assets/clients/logo-client-07.png",
          "alt": "Logo Cliente"
        }
      ],
      "_template": "hero"
    }
  ],
  "problem": [
    {
      "srcImg": "/assets/art-problem.png",
      "h2": "Chega de processos ineficientes e resultados inconsistentes. ",
      "p": "Transforme o marketing do seu negócio com soluções inteligentes que eliminam o retrabalho, potencializam suas vendas e automatizam sua comunicação. dados, performance e crescimento, tudo que você precisa para alcançar seus resultados.",
      "list": [
        {
          "iconList": "/assets/PresentationChart.svg",
          "itemList": "Engajamento elevado"
        },
        {
          "iconList": "/assets/CrosshairSimple.svg",
          "itemList": "Maior alcance de marca"
        },
        {
          "iconList": "/assets/ChartLineDown.svg",
          "itemList": "Menor rotatividade"
        },
        {
          "iconList": "/assets/ChatsTeardrop.svg",
          "itemList": "Mais usuários satisfeitos"
        }
      ],
      "_template": "problem"
    }
  ],
  "services": [
    {
      "h2": "Serviços para escalar o seu negócio no digital.",
      "p": "Adquira a solução que o seu negócio precisa.",
      "btn": "Garanta Agora",
      "btnLink": "cta",
      "inforService": [
        {
          "imgService": "/assets/",
          "nameService": "Serviço",
          "descriptionService": "Serviço\n"
        }
      ],
      "_template": "services"
    }
  ],
  "benefits": [
    {
      "h2": "Por que meus serviços são ideais para o seu crescimento digital?",
      "p": "Oferecemos uma parceria focada em resultados, com suporte contínuo e um excelente custo-benefício para você.",
      "btn": "Entrar em contato",
      "btnLink": "cta",
      "listBenefits": [
        {
          "iconBenefits": "/assets/TrendUp.svg",
          "nameBenefits": "Entrega e Excelência",
          "descriptionBenefits": "Metodologia precisa e execução eficiente que garantem resultados sólidos.\n"
        },
        {
          "iconBenefits": "/assets/ChatTeardropText.svg",
          "nameBenefits": "Suporte eficaz",
          "descriptionBenefits": "Nossa parceria vai além da entrega, suporte eficiente.\n"
        },
        {
          "iconBenefits": "/assets/Coins.svg",
          "nameBenefits": "Custo-Benefício",
          "descriptionBenefits": "Qualidade de ponta com preços justo.\n"
        }
      ],
      "_template": "benefits"
    }
  ],
  "method": [
    {
      "h2": "Como alcançamos resultados com nossa Metodologia.",
      "p": "Uma abordagem completa que une estratégia, execução constante e uma metodologia única para entregar resultados digitais duradouros.",
      "listMethod": [
        {
          "iconMethod": "/assets/Iconografia.svg",
          "nameMethod": "Planejamento Estratégico",
          "descriptionMethod": "Reunião inicial para entender seu negócio, definir metas e construir uma estratégia personalizada.\n"
        },
        {
          "iconMethod": "/assets/Iconografia.svg",
          "nameMethod": "Aplicação e Otimização",
          "descriptionMethod": "Reuniões mensais para análise de resultados e melhorias contínuas, com relatórios detalhados.\n"
        },
        {
          "iconMethod": "/assets/Iconografia.svg",
          "nameMethod": "Metódos Ágeis",
          "descriptionMethod": "Aplicação de uma metodologia exclusiva para um desenvolvimento digital eficaz e sustentável.\n"
        }
      ],
      "_template": "method"
    }
  ],
  "professional": [
    {
      "photo": "",
      "h1": "Kalaço Júnior",
      "h3": "Olá, praze",
      "h4": "Gestor de Trafégo",
      "description": "Especialista em marketing digital com foco em vendas e resultados, atuo na criação de soluções personalizadas que destacam marcas em um mercado competitivo. Com uma abordagem prática e orientada a dados, transformo a visão dos clientes em estratégias digitais que realmente entregam resultados. Minha experiência em projetos variados, do desenvolvimento à execução, garante uma adaptação eficaz às necessidades de cada negócio, sempre visando o crescimento e a lucratividade.\n",
      "_template": "professional"
    }
  ]
}